{
  "main": {
    "id": "8b8793ae37c2d9c1",
    "type": "split",
    "children": [
      {
        "id": "692ea3f9f647c63e",
        "type": "tabs",
        "children": [
          {
            "id": "bf7a1a63ca889591",
            "type": "leaf",
            "state": {
              "type": "empty",
              "state": {},
              "icon": "lucide-file",
              "title": "New tab"
            }
          }
        ]
      }
    ],
    "direction": "vertical"
  },
  "left": {
    "id": "405380e91106ac36",
    "type": "split",
    "children": [
      {
        "id": "030224792a9d33f8",
        "type": "tabs",
        "children": [
          {
            "id": "d0c9d1061441ad77",
            "type": "leaf",
            "state": {
              "type": "file-explorer",
              "state": {
                "sortOrder": "alphabetical",
                "autoReveal": false
              },
              "icon": "lucide-folder-closed",
              "title": "Files"
            }
          },
          {
            "id": "f5f664a3ce09c1d6",
            "type": "leaf",
            "state": {
              "type": "search",
              "state": {
                "query": "",
                "matchingCase": false,
                "explainSearch": false,
                "collapseAll": false,
                "extraContext": false,
                "sortOrder": "alphabetical"
              },
              "icon": "lucide-search",
              "title": "Search"
            }
          },
          {
            "id": "2fefac2ad688f479",
            "type": "leaf",
            "state": {
              "type": "bookmarks",
              "state": {},
              "icon": "lucide-bookmark",
              "title": "Bookmarks"
            }
          }
        ]
      }
    ],
    "direction": "horizontal",
    "width": 300
  },
  "right": {
    "id": "f8a89fa20e26a927",
    "type": "split",
    "children": [
      {
        "id": "fe63c40478bb4346",
        "type": "tabs",
        "children": [
          {
            "id": "e79f1f393806ebce",
            "type": "leaf",
            "state": {
              "type": "backlink",
              "state": {
                "collapseAll": false,
                "extraContext": false,
                "sortOrder": "alphabetical",
                "showSearch": false,
                "searchQuery": "",
                "backlinkCollapsed": false,
                "unlinkedCollapsed": true
              },
              "icon": "links-coming-in",
              "title": "Backlinks"
            }
          },
          {
            "id": "ee9c210debed4418",
            "type": "leaf",
            "state": {
              "type": "outgoing-link",
              "state": {
                "linksCollapsed": false,
                "unlinkedCollapsed": true
              },
              "icon": "links-going-out",
              "title": "Outgoing links"
            }
          },
          {
            "id": "9bf6c4da89a78ebc",
            "type": "leaf",
            "state": {
              "type": "tag",
              "state": {
                "sortOrder": "frequency",
                "useHierarchy": true,
                "showSearch": false,
                "searchQuery": ""
              },
              "icon": "lucide-tags",
              "title": "Tags"
            }
          },
          {
            "id": "1fd2876d77c5b633",
            "type": "leaf",
            "state": {
              "type": "outline",
              "state": {
                "followCursor": false,
                "showSearch": false,
                "searchQuery": ""
              },
              "icon": "lucide-list",
              "title": "Outline"
            }
          }
        ]
      }
    ],
    "direction": "horizontal",
    "width": 300,
    "collapsed": true
  },
  "left-ribbon": {
    "hiddenItems": {
      "switcher:Open quick switcher": false,
      "graph:Open graph view": false,
      "canvas:Create new canvas": false,
      "daily-notes:Open today's daily note": false,
      "templates:Insert template": false,
      "command-palette:Open command palette": false,
      "obsidian-to-anki-plugin:Obsidian_to_Anki - Scan Vault": false
    }
  },
  "active": "bf7a1a63ca889591",
  "lastOpenFiles": [
    "nix/what are nix overlays.md",
    "nix/what arguments do nix overlays take.md",
    "nix/how do nix overlays modify packages.md",
    "nix/how can overlays be used in standalone nix code.md",
    "nix/how can overlays be used in nix configuration.md",
    "nix/how can nix overlays be used in home manager.md",
    "nix/what are the advantages of nix overlays.md",
    "nix/what is the difference between self super and final prev in overlays.md",
    "nix/what do final and prev represent in nix overlays.md",
    "nix/what do self and super represent in overlays.md",
    "nix/why was final prev introduced.md",
    "nix/when should you use self super.md",
    "nix/when should you use final prev.md",
    "kotlin/buildMap function.md",
    "clitools/extract endings of strings that start with a specific prefix using awk.md",
    "nix/differences between self super and final prev.md",
    "linux/what is a bind mount.md",
    "linux/how does a bind mount differ from a symlink.md",
    "linux/can changes in a bind mount affect the original location.md",
    "linux/how to create a bind mount.md",
    "gradle/what does the --continue flag do.md",
    "gradle/what does the --rerun-tasks flag do.md",
    "gradle/how to reexecute all gradle tasks.md",
    "gradle/what does -s flag do.md",
    "shell/what is a login shell.md",
    "shell/what is the difference between login and non-login shell.md",
    "templates"
  ]
}